nerddiary/__init__.py
nerddiary/asynctools/__init__.py
nerddiary/asynctools/asyncapp.py
nerddiary/asynctools/delayedsignal.py
nerddiary/cli.py
nerddiary/client/__init__.py
nerddiary/client/client.py
nerddiary/client/config.py
nerddiary/client/rpc.py
nerddiary/data/__init__.py
nerddiary/data/crypto.py
nerddiary/data/data.py
nerddiary/error/error.py
nerddiary/job/__init__.py
nerddiary/job/job.py
nerddiary/log.py
nerddiary/poll/__init__.py
nerddiary/poll/poll.py
nerddiary/poll/question.py
nerddiary/poll/type.py
nerddiary/poll/workflow.py
nerddiary/primitive/__init__.py
nerddiary/primitive/timezone.py
nerddiary/primitive/valuelabel.py
nerddiary/report/__init__.py
nerddiary/report/report.py
nerddiary/server/__init__.py
nerddiary/server/api/__init__.py
nerddiary/server/api/api_v1/__init__.py
nerddiary/server/api/api_v1/routers/__init__.py
nerddiary/server/api/api_v1/routers/logs.py
nerddiary/server/api/api_v1/routers/session.py
nerddiary/server/api/api_v1/routers/websocket.py
nerddiary/server/config.py
nerddiary/server/dependencies.py
nerddiary/server/main.py
nerddiary/server/mixins/__init__.py
nerddiary/server/mixins/pollmixin.py
nerddiary/server/mixins/sessionmixin.py
nerddiary/server/proto.py
nerddiary/server/schema.py
nerddiary/server/server.py
nerddiary/server/session/__init__.py
nerddiary/server/session/session.py
nerddiary/server/session/status.py
nerddiary/user/__init__.py
nerddiary/user/user.py
nerddiary/utils/sensitive.py
nerddiary-0.3.2.dist-info/entry_points.txt
nerddiary-0.3.2.dist-info/LICENSE
nerddiary-0.3.2.dist-info/WHEEL
nerddiary-0.3.2.dist-info/METADATA
nerddiary-0.3.2.dist-info/RECORD
